{"name":"Remove products from cart","id":"go-to-the-linio.com.co-page-and-enter-the-home-category-and-select-a-product-from-the-mattresses-section;remove-products-from-cart","testSteps":[{"number":1,"description":"Given the user is in the application https://www.linio.com.co/","duration":1,"startTime":"2022-05-16T21:32:17.502-05:00[America/Bogota]","result":"PENDING","precondition":false,"level":0},{"number":2,"description":"When the user selects the shopping cart","duration":1,"startTime":"2022-05-16T21:32:17.503-05:00[America/Bogota]","result":"IGNORED","precondition":false,"level":0},{"number":3,"description":"Then the user removes the products from the shopping cart","duration":0,"startTime":"2022-05-16T21:32:17.504-05:00[America/Bogota]","result":"IGNORED","precondition":false,"level":0},{"number":4,"description":"And the user sees the message \"There are no products in your cart\"","duration":1,"startTime":"2022-05-16T21:32:17.505-05:00[America/Bogota]","result":"IGNORED","precondition":false,"level":0}],"userStory":{"id":"go-to-the-linio.com.co-page-and-enter-the-home-category-and-select-a-product-from-the-mattresses-section","storyName":"go to the Linio.com.co page and enter the Home category and select a product from the mattresses section","path":"src/test/resources/features/select_product.feature","narrative":"  Me as a user of the application Linio.com.co\n  I need to select a product\n  to add it to the shopping cart and when removing them show a message","type":"feature"},"featureTag":{"name":"Features/go to the Linio.com.co page and enter the Home category and select a product from the mattresses section","type":"feature","displayName":"Features/go to the Linio.com.co page and enter the Home category and select a product from the mattresses section"},"title":"Remove products from cart","tags":[{"name":"go to the Linio.com.co page and enter the Home category and select a product from the mattresses section","type":"feature","displayName":"go to the Linio.com.co page and enter the Home category and select a product from the mattresses section"}],"startTime":"2022-05-16T21:32:17.498-05:00[America/Bogota]","duration":8,"projectKey":"","annotatedResult":"PENDING","manual":false,"testSource":"Cucumber","result":"PENDING"}